field_mapper/__init__.py
field_mapper/mapper.py
field_mapper/mapper1.py
field_mapper/exc/__init__.py
field_mapper/exc/exception.py
field_mapper/test/__init__.py
field_mapper/test/duplicates_usage.py
field_mapper/test/nested_usage.py
field_mapper/test/position_usage.py
field_mapper/test/test.py
field_mapper/test/usage.py
field_mapper/test/usage_for_duplicates_data.py
field_mapper-0.2.2.dist-info/METADATA
field_mapper-0.2.2.dist-info/WHEEL
field_mapper-0.2.2.dist-info/top_level.txt
field_mapper-0.2.2.dist-info/RECORD
