Metadata-Version: 2.1
Name: field-mapper
Version: 0.2.2
Summary: Field Mapper a Python library for seamless data field validation, transformation, and mapping with support for types, lengths, and custom rules.
Home-page: https://github.com/aip777/field-mapper
Author: Ariful Islam Palash
Author-email: ariful.islamk777@gmail.com
Maintainer: Ariful Islam, Md Lutfor Rahman
Project-URL: Bug Tracker, https://github.com/aip777/field-mapper/issues
Classifier: Programming Language :: Python :: 3
Classifier: License :: OSI Approved :: MIT License
Classifier: Operating System :: OS Independent
Requires-Python: >=3.7
